_src/__init__.py
_src/mcts.py
tree_search-0.1.0.dist-info/METADATA
tree_search-0.1.0.dist-info/WHEEL
tree_search-0.1.0.dist-info/RECORD
